dm_robotics/panda/__init__.py
dm_robotics/panda/arm.py
dm_robotics/panda/arm_constants.py
dm_robotics/panda/environment.py
dm_robotics/panda/gripper.py
dm_robotics/panda/gripper_constants.py
dm_robotics/panda/hardware.py
dm_robotics/panda/parameters.py
dm_robotics/panda/run_loop.py
dm_robotics/panda/utils.py
dm_robotics/panda/assets/panda/NOTICE
dm_robotics/panda/assets/panda/finger.obj
dm_robotics/panda/assets/panda/hand.obj
dm_robotics/panda/assets/panda/link0.mtl
dm_robotics/panda/assets/panda/link0.obj
dm_robotics/panda/assets/panda/link1.obj
dm_robotics/panda/assets/panda/link2.obj
dm_robotics/panda/assets/panda/link3.obj
dm_robotics/panda/assets/panda/link4.obj
dm_robotics/panda/assets/panda/link5.obj
dm_robotics/panda/assets/panda/link6.obj
dm_robotics/panda/assets/panda/link7.obj
dm_robotics/panda/assets/panda/panda.png
dm_robotics/panda/assets/panda/panda.xml
dm_robotics/panda/assets/panda/panda_hand.xml
dm_robotics_panda-0.4.8.dist-info/METADATA
dm_robotics_panda-0.4.8.dist-info/WHEEL
dm_robotics_panda-0.4.8.dist-info/licenses/LICENSE
dm_robotics_panda-0.4.8.dist-info/RECORD
