Metadata-Version: 2.3
Name: dm-robotics-panda
Version: 0.4.8
Summary: Panda model for dm_robotics.
Project-URL: homepage, https://github.com/JeanElsner/dm_robotics_panda
Project-URL: documentation, https://jeanelsner.github.io/dm-robotics-panda/
Project-URL: repository, https://github.com/JeanElsner/dm_robotics_panda
Author-email: Jean Elsner <jean.elsner@tum.de>
License:                                  Apache License
License-File: LICENSE
Keywords: manipulation,panda,python,robotics,simulation
Classifier: Intended Audience :: Developers
Classifier: Intended Audience :: Science/Research
Classifier: License :: OSI Approved :: MIT License
Classifier: Programming Language :: Python :: 3.8
Classifier: Programming Language :: Python :: 3.9
Classifier: Programming Language :: Python :: 3.10
Classifier: Programming Language :: Python :: 3.11
Classifier: Programming Language :: Python :: 3.12
Classifier: Topic :: Scientific/Engineering
Requires-Python: <3.13,>=3.8
Requires-Dist: dm-env
Requires-Dist: dm-robotics-agentflow>=0.6.0
Requires-Dist: dm-robotics-controllers>=0.6.0
Requires-Dist: dm-robotics-geometry>=0.6.0
Requires-Dist: dm-robotics-manipulation>=0.6.0
Requires-Dist: dm-robotics-moma>=0.6.0
Requires-Dist: dm-robotics-transformations>=0.6.0
Requires-Dist: panda-python>=0.7.4
Provides-Extra: doc
Requires-Dist: furo; extra == 'doc'
Requires-Dist: sphinx; extra == 'doc'
Requires-Dist: sphinx-reredirects; extra == 'doc'
Requires-Dist: sphinxcontrib-youtube; extra == 'doc'
Provides-Extra: lint
Requires-Dist: anybadge; extra == 'lint'
Requires-Dist: pylint; extra == 'lint'
Provides-Extra: test
Requires-Dist: pytest; extra == 'test'
Requires-Dist: pytest-cov; extra == 'test'
